Metadata-Version: 2.1
Name: list-vpc-sc-supported-services
Version: 0.1.0
Summary: list services which support Google VPC Service Controls
Home-page: https://github.com/binxio/list-vpc-sc-supported-services
Author: Mark van Holsteijn
Author-email: mark@binx.io
License: Apache License 2.0
Platform: any
Classifier: Development Status :: 4 - Beta
Classifier: Environment :: Console
Classifier: Intended Audience :: Developers
Classifier: License :: OSI Approved :: BSD License
Classifier: Operating System :: POSIX
Classifier: Operating System :: MacOS
Classifier: Operating System :: Unix
Classifier: Operating System :: Microsoft :: Windows
Classifier: Programming Language :: Python
Classifier: Programming Language :: Python :: 3
License-File: LICENSE
